nulltype.py
nulltype-2.2.11.dist-info/DESCRIPTION.rst
nulltype-2.2.11.dist-info/METADATA
nulltype-2.2.11.dist-info/RECORD
nulltype-2.2.11.dist-info/WHEEL
nulltype-2.2.11.dist-info/metadata.json
nulltype-2.2.11.dist-info/top_level.txt
